OpenShiftCLI/__init__.py
OpenShiftCLI/errors.py
OpenShiftCLI/version.py
OpenShiftCLI/base/__init__.py
OpenShiftCLI/base/librarycomponent.py
OpenShiftCLI/cliclient/__init__.py
OpenShiftCLI/cliclient/apiclient.py
OpenShiftCLI/cliclient/cliclient.py
OpenShiftCLI/dataloader/__init__.py
OpenShiftCLI/dataloader/dataloader.py
OpenShiftCLI/dataloader/fileloader.py
OpenShiftCLI/dataloader/urlloader.py
OpenShiftCLI/dataparser/__init__.py
OpenShiftCLI/dataparser/dataparser.py
OpenShiftCLI/dataparser/jsonparser.py
OpenShiftCLI/dataparser/yamlparser.py
OpenShiftCLI/keywords/__init__.py
OpenShiftCLI/keywords/clusterrolebindings.py
OpenShiftCLI/keywords/clusterroles.py
OpenShiftCLI/keywords/configmaps.py
OpenShiftCLI/keywords/crds.py
OpenShiftCLI/keywords/groups.py
OpenShiftCLI/keywords/kfdefs.py
OpenShiftCLI/keywords/lists.py
OpenShiftCLI/keywords/pods.py
OpenShiftCLI/keywords/projects.py
OpenShiftCLI/keywords/rolebindings.py
OpenShiftCLI/keywords/roles.py
OpenShiftCLI/keywords/secrets.py
OpenShiftCLI/keywords/services.py
OpenShiftCLI/keywords/users.py
OpenShiftCLI/outputformatter/__init__.py
OpenShiftCLI/outputformatter/outputformatter.py
OpenShiftCLI/outputformatter/plaintextformatter.py
OpenShiftCLI/outputstreamer/__init__.py
OpenShiftCLI/outputstreamer/logstreamer.py
OpenShiftCLI/outputstreamer/outputstreamer.py
robotframework_OpenShiftCLI-1.0.0.dist-info/LICENSE
robotframework_OpenShiftCLI-1.0.0.dist-info/METADATA
robotframework_OpenShiftCLI-1.0.0.dist-info/WHEEL
robotframework_OpenShiftCLI-1.0.0.dist-info/top_level.txt
robotframework_OpenShiftCLI-1.0.0.dist-info/zip-safe
robotframework_OpenShiftCLI-1.0.0.dist-info/RECORD
